Metadata-Version: 1.1
Name: pysurgeon
Version: 0.1.0
Summary: Surgically implant Python docstrings within source code
Home-page: https://github.com/ex0dus-0x/pysurgeon
Author: Alan <ex0dus@codemuch.tech>
Author-email: UNKNOWN
License: UNKNOWN
Download-URL: https://github.com/ex0dus-0x/pysurgeon/archive/v0.1.0
Platform: UNKNOWN
